{
    "port": 443,
    "http2": true,
    "https": true,
    "rootPath": "C:/files/testserverdir/",
    "staticPath": "static",
    "apiPath": "api",
    "socket": "socket/socket",
    "logPath": "log",
    "errPagePath": "error",
    "https_key": "certificate/key.pem",
    "https_cert": "certificate/cert.pem",
    "apiHeaders": {
        "Content-Type": "application/json; utf-8",
        "Access-Control-Allow-Origin": "*",
        "Access-Control-Allow-Methods": "*"
    },
    "apiStringify": "json",
    "nomatch": "static/index.html",
    "staticCache": 10
}